datajoint_plus/__init__.py
datajoint_plus/base.py
datajoint_plus/blob.py
datajoint_plus/compatibility.py
datajoint_plus/definition.py
datajoint_plus/enum.py
datajoint_plus/errors.py
datajoint_plus/hash.py
datajoint_plus/heading.py
datajoint_plus/jobs.py
datajoint_plus/logging.py
datajoint_plus/motif.py
datajoint_plus/motif_base.py
datajoint_plus/schema.py
datajoint_plus/table.py
datajoint_plus/user_tables.py
datajoint_plus/utils.py
datajoint_plus/validation.py
datajoint_plus/version.py
datajoint_plus/config/__init__.py
datajoint_plus/config/logging/__init__.py
datajoint_plus/config/logging/load_config.py
datajoint_plus/config/logging/templates/__init__.py
datajoint_plus/config/logging/templates/console.yml
datajoint_plus/config/logging/templates/filehandler_basic.yml
datajoint_plus/config/logging/templates/filehandler_rotating.yml
datajoint_plus/config/logging/templates/filehandler_timed_rotating.yml
datajoint_plus-0.1.9.dist-info/LICENSE
datajoint_plus-0.1.9.dist-info/METADATA
datajoint_plus-0.1.9.dist-info/WHEEL
datajoint_plus-0.1.9.dist-info/top_level.txt
datajoint_plus-0.1.9.dist-info/RECORD
