Metadata-Version: 2.1
Name: datajoint-plus
Version: 0.1.9
Summary: A DataJoint extension that integrates hashes and other features.
Author: Stelios Papadopoulos
Author-email: spapadop@bcm.edu
License: GNU LGPL
Requires-Python: ~=3.6
License-File: LICENSE
Requires-Dist: envyaml
Requires-Dist: simplejson
Requires-Dist: datajoint ==0.12.9
